impyp/__init__.py
impyp/core.py
impyp-1.0.0.dist-info/licenses/LICENSE
impyp-1.0.0.dist-info/METADATA
impyp-1.0.0.dist-info/WHEEL
impyp-1.0.0.dist-info/entry_points.txt
impyp-1.0.0.dist-info/top_level.txt
impyp-1.0.0.dist-info/RECORD
