Metadata-Version: 2.4
Name: imPYP
Version: 1.0.0
Summary: Python library installer/uninstaller
Author: KsDev
Requires-Python: >=3.8
License-File: LICENSE
Requires-Dist: rich
Dynamic: author
Dynamic: license-file
Dynamic: requires-dist
Dynamic: requires-python
Dynamic: summary
